yubikey_manager_lib.py
yubikey_manager_repl.py
yubikey_manager_lib-0.2.0.dist-info/METADATA
yubikey_manager_lib-0.2.0.dist-info/WHEEL
yubikey_manager_lib-0.2.0.dist-info/entry_points.txt
yubikey_manager_lib-0.2.0.dist-info/RECORD
