Metadata-Version: 2.1
Name: yubikey-manager-lib
Version: 0.2.0
Summary: Run yubikey-manager commands programmatically
License: GPL-3.0
Author: Dick Marinus
Requires-Python: >=3.9,<4.0
Classifier: License :: OSI Approved :: GNU General Public License v3 (GPLv3)
Classifier: Programming Language :: Python :: 3
Classifier: Programming Language :: Python :: 3.9
Classifier: Programming Language :: Python :: 3.10
Classifier: Programming Language :: Python :: 3.11
Classifier: Programming Language :: Python :: 3.12
Requires-Dist: yubikey-manager (>=5.3.0)
